plugins/__init__.py
plugins/read_data.py
pyexafs/__init__.py
pyexafs/__main__.py
pyexafs/criteria.json
pyexafs/criteria_json.py
pyexafs/pyexafs.py
pyexafs/example_data/LABORATORY/.gitkeep
pyexafs/example_data/SYNCHROTRON/.gitkeep
pyexafs/example_data/SYNCHROTRON/Co_metal_Delta.txt
pyexafs/example_data/SYNCHROTRON/Cu2O Cu K Elettra.txt
pyexafs/example_data/SYNCHROTRON/Mo_foil Mo K ROCK Soleil.txt
pyexafs/example_data/SYNCHROTRON/Nb_scan14_raw_BL8.txt
pyexafs/example_data/SYNCHROTRON/Pt_foil Pt L3 SAMBA Soleil.txt
pyexafs/example_data/SYNCHROTRON/Pt_foil_Pt L3 SLS.txt
pyexafs-1.0.0b9.dist-info/LICENSE
pyexafs-1.0.0b9.dist-info/METADATA
pyexafs-1.0.0b9.dist-info/WHEEL
pyexafs-1.0.0b9.dist-info/entry_points.txt
pyexafs-1.0.0b9.dist-info/top_level.txt
pyexafs-1.0.0b9.dist-info/RECORD
