Metadata-Version: 2.1
Name: pyexafs
Version: 1.0.0b9
Summary: A simple package for fast analysis of EXAFS data
Author-email: Sebastian Paripsa <paripsa@uni-wuppertal.de>
License: MIT License
Project-URL: Homepage, https://github.com/San-WierPa/pyexafs
Keywords: research-and-development,exafs,data-science
Classifier: License :: OSI Approved :: MIT License
Classifier: Programming Language :: Python
Classifier: Programming Language :: Python :: 3
Classifier: Development Status :: 4 - Beta
License-File: LICENSE
Requires-Dist: xraylarch ==0.9.66
Requires-Dist: lmfit ==1.1.0
Requires-Dist: asteval ==0.9.33
Requires-Dist: cchardet ==2.1.7
Requires-Dist: certifi ==2024.2.2
Requires-Dist: charset-normalizer ==3.3.2
Requires-Dist: contourpy ==1.2.1
Requires-Dist: cycler ==0.12.1
Requires-Dist: exceptiongroup ==1.2.1
Requires-Dist: fabio ==2024.4.0
Requires-Dist: fonttools ==4.52.1
Requires-Dist: future ==1.0.0
Requires-Dist: greenlet ==3.0.3
Requires-Dist: h5py ==3.11.0
Requires-Dist: hdf5plugin ==4.4.0
Requires-Dist: idna ==3.7
Requires-Dist: imageio ==2.34.1
Requires-Dist: iniconfig ==2.0.0
Requires-Dist: joblib ==1.4.2
Requires-Dist: kiwisolver ==1.4.5
Requires-Dist: latexcodec ==3.0.0
Requires-Dist: lazy-loader ==0.4
Requires-Dist: lxml ==5.2.2
Requires-Dist: matplotlib ==3.7.0
Requires-Dist: monty ==2024.5.24
Requires-Dist: mpmath ==1.3.0
Requires-Dist: networkx ==3.3
Requires-Dist: numdifftools ==0.9.41
Requires-Dist: numexpr ==2.10.0
Requires-Dist: numpy ==1.24.2
Requires-Dist: packaging ==24.0
Requires-Dist: palettable ==3.3.3
Requires-Dist: pandas ==2.2.2
Requires-Dist: peakutils ==1.3.4
Requires-Dist: pillow ==10.3.0
Requires-Dist: platformdirs ==4.2.2
Requires-Dist: plotly ==5.22.0
Requires-Dist: pluggy ==1.5.0
Requires-Dist: ply ==3.11
Requires-Dist: psutil ==5.9.8
Requires-Dist: pybtex ==0.24.0
Requires-Dist: pycifrw ==4.4.6
Requires-Dist: pyfai ==2024.5.0
Requires-Dist: pymatgen ==2023.9.25
Requires-Dist: pyparsing ==3.1.2
Requires-Dist: pyshortcuts ==1.9.0
Requires-Dist: pytest ==8.2.1
Requires-Dist: python-dateutil ==2.9.0.post0
Requires-Dist: pytz ==2024.1
Requires-Dist: pyyaml ==6.0.1
Requires-Dist: requests ==2.32.2
Requires-Dist: ruamel-yaml ==0.18.6
Requires-Dist: ruamel-yaml-clib ==0.2.8
Requires-Dist: scikit-image ==0.23.2
Requires-Dist: scikit-learn ==1.5.0
Requires-Dist: scipy ==1.10.0
Requires-Dist: silx ==2.1.0
Requires-Dist: six ==1.16.0
Requires-Dist: spglib ==2.4.0
Requires-Dist: sqlalchemy ==2.0.30
Requires-Dist: sympy ==1.12
Requires-Dist: tabulate ==0.9.0
Requires-Dist: tenacity ==8.3.0
Requires-Dist: termcolor ==2.4.0
Requires-Dist: threadpoolctl ==3.5.0
Requires-Dist: tifffile ==2024.5.22
Requires-Dist: toml ==0.10.2
Requires-Dist: tomli ==2.0.1
Requires-Dist: tqdm ==4.66.4
Requires-Dist: typing-extensions ==4.12.0
Requires-Dist: tzdata ==2024.1
Requires-Dist: uncertainties ==3.1.7
Requires-Dist: urllib3 ==2.2.1
Requires-Dist: xraydb ==4.5.4
Provides-Extra: dev
Requires-Dist: black ; extra == 'dev'
Requires-Dist: isort ; extra == 'dev'
